flake8_coding.py
flake8_coding-1.3.2.dist-info/LICENSE
flake8_coding-1.3.2.dist-info/METADATA
flake8_coding-1.3.2.dist-info/WHEEL
flake8_coding-1.3.2.dist-info/entry_points.txt
flake8_coding-1.3.2.dist-info/top_level.txt
flake8_coding-1.3.2.dist-info/RECORD
