Metadata-Version: 1.1
Name: flake8-coding
Version: 1.3.2
Summary: Adds coding magic comment checks to flake8
Home-page: https://github.com/tk0miya/flake8-coding
Author: Takeshi KOMIYA
Author-email: i.tkomiya@gmail.com
License: Apache License 2.0
Keywords: pep8 flake8 coding
Platform: UNKNOWN
Classifier: Development Status :: 3 - Alpha
Classifier: Programming Language :: Python
Classifier: Programming Language :: Python :: 2
Classifier: Programming Language :: Python :: 2.7
Classifier: Programming Language :: Python :: 3
Classifier: Programming Language :: Python :: 3.3
Classifier: Programming Language :: Python :: 3.4
Classifier: Topic :: Software Development
